filesmith/__init__.py
filesmith/core.py
filesmith-0.1.0.dist-info/licenses/LICENSE
filesmith-0.1.0.dist-info/METADATA
filesmith-0.1.0.dist-info/WHEEL
filesmith-0.1.0.dist-info/entry_points.txt
filesmith-0.1.0.dist-info/top_level.txt
filesmith-0.1.0.dist-info/RECORD
