Metadata-Version: 2.4
Name: filesmith
Version: 0.1.0
Summary: A utility for copying files based on pattern matching
Author-email: Eiichi YAMAMOTO <info@yeiichi.com>
License: MIT
Project-URL: Homepage, https://github.com/yeiichi/filesmith
Project-URL: Repository, https://github.com/yeiichi/filesmith.git
Project-URL: Issues, https://github.com/yeiichi/filesmith/issues
Classifier: Development Status :: 3 - Alpha
Classifier: Environment :: Console
Classifier: Intended Audience :: Developers
Classifier: License :: OSI Approved :: MIT License
Classifier: Operating System :: OS Independent
Classifier: Programming Language :: Python :: 3
Classifier: Programming Language :: Python :: 3.9
Classifier: Topic :: System :: Filesystems
Requires-Python: >=3.9
License-File: LICENSE
Provides-Extra: dev
Requires-Dist: pytest>=7.0; extra == "dev"
Requires-Dist: sphinx>=4.0; extra == "dev"
Dynamic: license-file
